reebundle/__init__.py
reebundle/construct.py
reebundle/distance.py
reebundle/events.py
reebundle/visualization.py
reebundle-0.1.2.dist-info/licenses/LICENSE
reebundle-0.1.2.dist-info/METADATA
reebundle-0.1.2.dist-info/WHEEL
reebundle-0.1.2.dist-info/top_level.txt
reebundle-0.1.2.dist-info/RECORD
