Metadata-Version: 2.4
Name: reebundle
Version: 0.1.2
Summary: A package for creating Reeb graphs for diffusion MRI tractography
Author: S Shailja, V. Bhagavatula, M. Cieslak, J. M. Vettel,, S. T. Grafton, B. S. Manjunath
License:                                  Apache License
Project-URL: Homepage, https://github.com/s-shailja/reebundle
Project-URL: Documentation, https://github.com/s-shailja/reebundle
Project-URL: Issues, https://github.com/s-shailja/reebundle/issues
Requires-Python: >=3.8
License-File: LICENSE
Provides-Extra: test
Requires-Dist: pytest; extra == "test"
Dynamic: license-file
